<?xml version="1.0" encoding="UTF-8"?>
<configuration>
    <springProperty scope="context" name="APP_NAME" source="spring.application.name" defaultValue="auth-service"/>

    <!-- Console appender with pattern -->
    <appender name="CONSOLE" class="ch.qos.logback.core.ConsoleAppender">
        <encoder>
            <pattern>%d{yyyy-MM-dd HH:mm:ss.SSS} [%thread] %-5level %logger{36} - %msg%n</pattern>
        </encoder>
    </appender>

    <!-- File appender for all logs -->
    <appender name="FILE" class="ch.qos.logback.core.rolling.RollingFileAppender">
        <file>logs/auth-server.log</file>
        <encoder>
            <pattern>%d{yyyy-MM-dd HH:mm:ss.SSS} [%thread] %-5level %logger{36} - %msg%n</pattern>
        </encoder>
        <rollingPolicy class="ch.qos.logback.core.rolling.TimeBasedRollingPolicy">
            <fileNamePattern>logs/auth-server-%d{yyyy-MM-dd}.%i.log</fileNamePattern>
            <timeBasedFileNamingAndTriggeringPolicy class="ch.qos.logback.core.rolling.SizeAndTimeBasedFNATP">
                <maxFileSize>10MB</maxFileSize>
            </timeBasedFileNamingAndTriggeringPolicy>
            <maxHistory>30</maxHistory>
        </rollingPolicy>
    </appender>

    <!-- Error file appender -->
    <appender name="ERROR_FILE" class="ch.qos.logback.core.rolling.RollingFileAppender">
        <file>logs/auth-server-error.log</file>
        <filter class="ch.qos.logback.classic.filter.ThresholdFilter">
            <level>ERROR</level>
        </filter>
        <encoder>
            <pattern>%d{yyyy-MM-dd HH:mm:ss.SSS} [%thread] %-5level %logger{36} - %msg%n</pattern>
        </encoder>
        <rollingPolicy class="ch.qos.logback.core.rolling.TimeBasedRollingPolicy">
            <fileNamePattern>logs/auth-server-error-%d{yyyy-MM-dd}.%i.log</fileNamePattern>
            <timeBasedFileNamingAndTriggeringPolicy class="ch.qos.logback.core.rolling.SizeAndTimeBasedFNATP">
                <maxFileSize>10MB</maxFileSize>
            </timeBasedFileNamingAndTriggeringPolicy>
            <maxHistory>30</maxHistory>
        </rollingPolicy>
    </appender>

    <!-- Audit file appender for security events -->
    <appender name="AUDIT_FILE" class="ch.qos.logback.core.rolling.RollingFileAppender">
        <file>logs/auth-server-audit.log</file>
        <encoder>
            <pattern>%d{yyyy-MM-dd HH:mm:ss.SSS} - %msg%n</pattern>
        </encoder>
        <rollingPolicy class="ch.qos.logback.core.rolling.TimeBasedRollingPolicy">
            <fileNamePattern>logs/auth-server-audit-%d{yyyy-MM-dd}.%i.log</fileNamePattern>
            <timeBasedFileNamingAndTriggeringPolicy class="ch.qos.logback.core.rolling.SizeAndTimeBasedFNATP">
                <maxFileSize>10MB</maxFileSize>
            </timeBasedFileNamingAndTriggeringPolicy>
            <maxHistory>90</maxHistory>
        </rollingPolicy>
    </appender>

    <!-- Async wrapper for better performance -->
    <appender name="ASYNC_FILE" class="ch.qos.logback.classic.AsyncAppender">
        <appender-ref ref="FILE"/>
        <queueSize>512</queueSize>
        <discardingThreshold>0</discardingThreshold>
    </appender>

    <appender name="ASYNC_ERROR_FILE" class="ch.qos.logback.classic.AsyncAppender">
        <appender-ref ref="ERROR_FILE"/>
        <queueSize>512</queueSize>
        <discardingThreshold>0</discardingThreshold>
    </appender>

    <!-- Logger for audit events -->
    <logger name="AUDIT" level="INFO" additivity="false">
        <appender-ref ref="AUDIT_FILE"/>
    </logger>

    <!-- Root logger -->
    <root level="INFO">
        <appender-ref ref="CONSOLE"/>
        <appender-ref ref="ASYNC_FILE"/>
        <appender-ref ref="ASYNC_ERROR_FILE"/>
    </root>

    <!-- Spring Profile specific configurations -->
    <springProfile name="dev">
        <root level="DEBUG">
            <appender-ref ref="CONSOLE"/>
            <appender-ref ref="ASYNC_FILE"/>
            <appender-ref ref="ASYNC_ERROR_FILE"/>
        </root>
    </springProfile>

    <springProfile name="prod">
        <root level="INFO">
            <appender-ref ref="CONSOLE"/>
            <appender-ref ref="ASYNC_FILE"/>
            <appender-ref ref="ASYNC_ERROR_FILE"/>
        </root>
    </springProfile>
</configuration>
